Metadata-Version: 2.1
Name: wiselog
Version: 0.0.1
Summary: Wiselog
Author: MF
